tum_esm_signal/__init__.py
tum_esm_signal/client.py
tum_esm_signal/pocketbase.py
tum_esm_signal/py.typed
tum_esm_signal-0.3.0.dist-info/METADATA
tum_esm_signal-0.3.0.dist-info/WHEEL
tum_esm_signal-0.3.0.dist-info/RECORD
